<?xml version="1.0" encoding="utf-8"?>
<django-objects version="1.0">
    <object pk="1" model="giftreg.category">
        <field type="CharField" name="CategoryName">
            Books
        </field>
    </object>
    <object pk="2" model="giftreg.category">
        <field type="CharField" name="CategoryName">
            Music
        </field>
    </object>
    <object pk="3" model="giftreg.category">
        <field type="CharField" name="CategoryName">
            Video Games
        </field>
    </object>
    <object pk="4" model="giftreg.category">
        <field type="CharField" name="CategoryName">
            Clothing
        </field>
    </object>
    <object pk="5" model="giftreg.category">
        <field type="CharField" name="CategoryName">
            Movies/DVD
        </field>
    </object>
    <object pk="6" model="giftreg.category">
        <field type="CharField" name="CategoryName">
            Gift Certificates
        </field>
    </object>
    <object pk="7" model="giftreg.category">
        <field type="CharField" name="CategoryName">
            Hobbies
        </field>
    </object>
    <object pk="8" model="giftreg.category">
        <field type="CharField" name="CategoryName">
            Household
        </field>
    </object>
    <object pk="9" model="giftreg.category">
        <field type="CharField" name="CategoryName">
            Electronics
        </field>
    </object>
    <object pk="10" model="giftreg.category">
        <field type="CharField" name="CategoryName">
            Ornaments/Figurines
        </field>
    </object>
    <object pk="11" model="giftreg.category">
        <field type="CharField" name="CategoryName">
            Automotive
        </field>
    </object>
    <object pk="12" model="giftreg.category">
        <field type="CharField" name="CategoryName">
            Toys
        </field>
    </object>
    <object pk="13" model="giftreg.category">
        <field type="CharField" name="CategoryName">
            Jewellery
        </field>
    </object>
    <object pk="14" model="giftreg.category">
        <field type="CharField" name="CategoryName">
            Computer
        </field>
    </object>
    <object pk="15" model="giftreg.category">
        <field type="CharField" name="CategoryName">
            Games
        </field>
    </object>
    <object pk="16" model="giftreg.category">
        <field type="CharField" name="CategoryName">
            Tools
        </field>
    </object>
</django-objects>
